dotevals_datasets/__init__.py
dotevals_datasets/bfcl.py
dotevals_datasets/gsm8k.py
dotevals_datasets/humaneval.py
dotevals_datasets/mmlu.py
dotevals_datasets/sroie.py
dotevals_datasets-0.8.0.dist-info/METADATA
dotevals_datasets-0.8.0.dist-info/WHEEL
dotevals_datasets-0.8.0.dist-info/entry_points.txt
dotevals_datasets-0.8.0.dist-info/top_level.txt
dotevals_datasets-0.8.0.dist-info/RECORD
