Metadata-Version: 2.4
Name: dotevals-datasets
Version: 0.8.0
Summary: Standard datasets for dotevals LLM evaluations
Author-email: ".txt" <contact@dottxt.ai>
Project-URL: repository, https://github.com/dottxt-ai/doteval-datasets
Requires-Python: >=3.10
Requires-Dist: dotevals
Requires-Dist: datasets
Requires-Dist: Pillow
Provides-Extra: test
Requires-Dist: pytest; extra == "test"
Requires-Dist: pytest-asyncio; extra == "test"
Requires-Dist: pytest-cov; extra == "test"
Requires-Dist: types-Pillow; extra == "test"
